django_autokit/__init__.py
django_autokit/cli.py
django_autokit/core.py
django_autokit/utils/__init__.py
django_autokit/utils/app_file_creator.py
django_autokit/utils/env_loader.py
django_autokit/utils/gen_gitignore.py
django_autokit/utils/settings_modifier.py
django_autokit/utils/settings_splitter.py
django_autokit-0.2.1.dist-info/LICENSE
django_autokit-0.2.1.dist-info/METADATA
django_autokit-0.2.1.dist-info/WHEEL
django_autokit-0.2.1.dist-info/entry_points.txt
django_autokit-0.2.1.dist-info/top_level.txt
django_autokit-0.2.1.dist-info/RECORD
