Metadata-Version: 2.1
Name: django-autokit
Version: 0.2.1
Summary: A CLI tool to automate Django project setup, including settings splitting, .env creation, and app boilerplate.
Author-email: "drey.tech" <oluwadamilareadeniye@yahoo.com>
License: MIT
Project-URL: Homepage, http://github.com/niyimarc/django_autokit
Project-URL: Issues, http://github.com/niyimarc/django_autokit/issues
Classifier: Framework :: Django
Classifier: Programming Language :: Python :: 3
Classifier: Operating System :: OS Independent
Classifier: Intended Audience :: Developers
Classifier: License :: OSI Approved :: MIT License
Classifier: Topic :: Software Development :: Code Generators
Classifier: Topic :: Software Development :: Libraries :: Python Modules
Requires-Python: >=3.7
License-File: LICENSE
Requires-Dist: python-dotenv
